tman/__init__.py
tman/__main__.py
tman/_config.py
tman/_runners.py
tman/py.typed
torrent_manager-0.2.0.dist-info/METADATA
torrent_manager-0.2.0.dist-info/WHEEL
torrent_manager-0.2.0.dist-info/entry_points.txt
torrent_manager-0.2.0.dist-info/top_level.txt
torrent_manager-0.2.0.dist-info/RECORD
