Metadata-Version: 2.1
Name: torrent-manager
Version: 0.2.0
Summary: Torrent manager enables you to download / seed your torrents on your own schedule.
Home-page: https://github.com/bbugyi200/tman
Author: Bryan M Bugyi
Author-email: bryanbugyi34@gmail.com
License: MIT license
Platform: UNKNOWN
Classifier: Development Status :: 3 - Alpha
Classifier: Intended Audience :: Developers
Classifier: License :: OSI Approved :: MIT License
Classifier: Natural Language :: English
Classifier: Programming Language :: Python :: 3
Classifier: Programming Language :: Python :: 3.8
Classifier: Programming Language :: Python :: 3.9
Classifier: Programming Language :: Python :: 3.10
Requires-Python: >=3.8
Requires-Dist: bolton-clack (~=0.3.1)
Requires-Dist: bolton-logrus (~=0.1.0)
